etl_package_auto1/__init__.py
etl_package_auto1/constants.py
etl_package_auto1/etl.py
etl_package_auto1/transformations.py
etl_package_auto1/utils.py
etl_package_auto1-0.0.13.dist-info/METADATA
etl_package_auto1-0.0.13.dist-info/WHEEL
etl_package_auto1-0.0.13.dist-info/top_level.txt
etl_package_auto1-0.0.13.dist-info/RECORD
