Metadata-Version: 2.1
Name: etl-package-auto1
Version: 0.0.13
Summary: ETL Package Auto1
Home-page: UNKNOWN
Author: Muhammad Aqib
Author-email: <inbox.aqib@gmail.com>
License: UNKNOWN
Keywords: etl,auto1
Platform: UNKNOWN
Classifier: Development Status :: 1 - Planning
Classifier: Intended Audience :: Developers
Classifier: Programming Language :: Python :: 3
Classifier: Operating System :: Unix
Classifier: Operating System :: MacOS :: MacOS X
Classifier: Operating System :: Microsoft :: Windows
